HISTORY.rst
LICENSE
MANIFEST.in
README.rst
setup.py
D2LValence_Util.egg-info/PKG-INFO
D2LValence_Util.egg-info/SOURCES.txt
D2LValence_Util.egg-info/dependency_links.txt
D2LValence_Util.egg-info/requires.txt
D2LValence_Util.egg-info/top_level.txt
d2lvalence_util/__init__.py
d2lvalence_util/data.py
d2lvalence_util/service.py