Metadata-Version: 1.1
Name: D2LValence-Util
Version: 0.1.16
Summary: D2LValence utility library for Python.
Home-page: http://www.desire2learn.com/r/valencehome
Author: Desire2Learn Inc.
Author-email: Valence@Desire2Learn.com
License: -*- coding: utf-8 -*-
